adeval/__init__.py
adeval/__main__.py
adeval/au_pro.py
adeval/cuda_mem_effic.py
adeval/iterative.py
adeval/iterative_cuda.py
adeval/mem_effic.py
adeval/metrics.py
adeval/reference_impl.py
adeval/utils.py
ADEval-1.1.0.dist-info/LICENSE
ADEval-1.1.0.dist-info/METADATA
ADEval-1.1.0.dist-info/WHEEL
ADEval-1.1.0.dist-info/top_level.txt
ADEval-1.1.0.dist-info/RECORD
