Metadata-Version: 2.1
Name: ADEval
Version: 1.1.0
Summary: Fast and Memory-efficient Routines for AUROC/AUPR/Pixel-AUPRO
Author: wing gan
License: ADEval, a python package for performance evaluation in Anomaly Detection
Project-URL: Homepage, https://github.com/winggan/adeval
Project-URL: Issues, https://github.com/winggan/adeval/issues
Classifier: Programming Language :: Python :: 3
Classifier: License :: OSI Approved :: BSD License
Classifier: Operating System :: OS Independent
Requires-Python: >=3.6
License-File: LICENSE
Requires-Dist: torch >=1.8.0
Requires-Dist: numpy >=1.19
Requires-Dist: opencv-python >=3.4
Requires-Dist: Pillow >=4.0
